aiobaidu/__init__.py
aiobaidu/bceutil.py
aiobaidu/face.py
aiobaidu-0.1.1.dist-info/DESCRIPTION.rst
aiobaidu-0.1.1.dist-info/METADATA
aiobaidu-0.1.1.dist-info/RECORD
aiobaidu-0.1.1.dist-info/WHEEL
aiobaidu-0.1.1.dist-info/metadata.json
aiobaidu-0.1.1.dist-info/top_level.txt
