Metadata-Version: 2.0
Name: aiobaidu
Version: 0.1.1
Summary: Baidu AIP SDK for asyncio
Home-page: https://github.com/yaroslav-dudar/aio-baidu
Author: https://github.com/yaroslav-dudar
Author-email: flayingfog@gmail.com
License: Apache License
Keywords: baidu,face,aiobaidu
Platform: UNKNOWN
Requires-Dist: aiohttp (>2.0)
